reptile/__init__.py
reptile/constants.py
reptile/helpers.py
reptile/ActFunctions/ActFunctions.py
reptile/ActFunctions/__init__.py
reptile/Constructor/Constructor.py
reptile/Constructor/__init__.py
reptile/Core/CPU.py
reptile/Core/Core.py
reptile/Core/GPU.py
reptile/Core/__init__.py
reptile/Layer/Layer.py
reptile/Layer/__init__.py
reptile/Network/Network.py
reptile/Network/__init__.py
reptile/__tests__/__init__.py
reptile/__tests__/tests.py
reptile/__tests__/imagesets/__init__.py
reptile/__tests__/imagesets/imagesets.py
reptile/__tests__/shapshots/__init__.py
reptile/__tests__/shapshots/shapshots.py
reptile_network-0.1.4.dist-info/LICENSE
reptile_network-0.1.4.dist-info/METADATA
reptile_network-0.1.4.dist-info/WHEEL
reptile_network-0.1.4.dist-info/top_level.txt
reptile_network-0.1.4.dist-info/RECORD
