Metadata-Version: 2.1
Name: reptile-network
Version: 0.1.4
Summary: Краткое описание coming soon...
Home-page: UNKNOWN
Author: sTonKs
Author-email: kisel@internet.ru
License: UNKNOWN
Platform: UNKNOWN
Classifier: Programming Language :: Python :: 3.8
Classifier: License :: OSI Approved :: MIT License
Classifier: Operating System :: OS Independent
Requires-Python: >=3.6
Requires-Dist: idx2numpy (==1.2.3)
Requires-Dist: numpy (==1.20.1)
